odoo/addons/ssi_hr_career_transition/README.rst
odoo/addons/ssi_hr_career_transition/__init__.py
odoo/addons/ssi_hr_career_transition/__manifest__.py
odoo/addons/ssi_hr_career_transition/hooks.py
odoo/addons/ssi_hr_career_transition/data/approval_template_data.xml
odoo/addons/ssi_hr_career_transition/data/ir_sequence_data.xml
odoo/addons/ssi_hr_career_transition/data/policy_template_data.xml
odoo/addons/ssi_hr_career_transition/data/sequence_template_data.xml
odoo/addons/ssi_hr_career_transition/i18n/ssi_hr_career_transition.pot
odoo/addons/ssi_hr_career_transition/migrations/14.0.2.0.0/post-migration.py
odoo/addons/ssi_hr_career_transition/models/__init__.py
odoo/addons/ssi_hr_career_transition/models/employee_career_transition.py
odoo/addons/ssi_hr_career_transition/models/employee_career_transition_type.py
odoo/addons/ssi_hr_career_transition/models/employee_career_transition_type_reason.py
odoo/addons/ssi_hr_career_transition/models/hr_employee.py
odoo/addons/ssi_hr_career_transition/models/res_company.py
odoo/addons/ssi_hr_career_transition/security/ir.model.access.csv
odoo/addons/ssi_hr_career_transition/security/ir_module_category_data.xml
odoo/addons/ssi_hr_career_transition/security/ir_rule_data.xml
odoo/addons/ssi_hr_career_transition/security/res_group_data.xml
odoo/addons/ssi_hr_career_transition/static/description/icon.png
odoo/addons/ssi_hr_career_transition/views/employee_career_transition_type_views.xml
odoo/addons/ssi_hr_career_transition/views/employee_career_transition_views.xml
odoo/addons/ssi_hr_career_transition/views/hr_employee_views.xml
odoo/addons/ssi_hr_career_transition/views/res_company_views.xml
odoo14_addon_ssi_hr_career_transition-14.0.2.4.0.dist-info/METADATA
odoo14_addon_ssi_hr_career_transition-14.0.2.4.0.dist-info/WHEEL
odoo14_addon_ssi_hr_career_transition-14.0.2.4.0.dist-info/top_level.txt
odoo14_addon_ssi_hr_career_transition-14.0.2.4.0.dist-info/RECORD
